asn_info/__init__.py
asn_info-0.4.dist-info/LICENSE
asn_info-0.4.dist-info/METADATA
asn_info-0.4.dist-info/WHEEL
asn_info-0.4.dist-info/top_level.txt
asn_info-0.4.dist-info/RECORD
