Metadata-Version: 2.1
Name: asn_info
Version: 0.4
Summary: A python library providing information about ASNs (AS Name, Country and MANRS membership)
Home-page: https://github.com/stucchimax/asn_info
Author: Massimiliano Stucchi
Author-email: max@stucchi.ch
License: BSD
Keywords: asn autonomous systems routing networking
Classifier: Intended Audience :: Developers
Classifier: Topic :: Software Development :: Libraries :: Python Modules
Classifier: Topic :: System :: Networking
Classifier: License :: OSI Approved :: BSD License
Classifier: Programming Language :: Python :: 3 :: Only
License-File: LICENSE
Requires-Dist: requests
